jumpcloud/__init__.py
jumpcloud/__main__.py
jumpcloud/jumpcloud.py
jumpcloud/reports/reports.py
jumpcloud-2.0.1.dist-info/LICENSE
jumpcloud-2.0.1.dist-info/METADATA
jumpcloud-2.0.1.dist-info/WHEEL
jumpcloud-2.0.1.dist-info/entry_points.txt
jumpcloud-2.0.1.dist-info/top_level.txt
jumpcloud-2.0.1.dist-info/RECORD
