Metadata-Version: 2.1
Name: jumpcloud
Version: 2.0.1
Summary: jumpcloud command for jumpcloud.com
Home-page: https://gitlab.com/krink/jumpcloud
Author: Karl Rink
Author-email: karl@rink.us
License: UNKNOWN
Project-URL: Bug Tracker, https://gitlab.com/krink/jumpcloud/issues
Platform: UNKNOWN
Classifier: Programming Language :: Python :: 3 :: Only
Classifier: License :: OSI Approved :: MIT License
Classifier: Operating System :: OS Independent
Classifier: Development Status :: 5 - Production/Stable
Classifier: Environment :: Console
Classifier: Intended Audience :: System Administrators
Classifier: Topic :: Utilities
Requires-Python: >=3.6
License-File: LICENSE
Requires-Dist: requests
